jinzhupy/__init__.py
jinzhupy/amqplib/__init__.py
jinzhupy/amqplib/defs.py
jinzhupy/amqplib/rabbitmq.py
jinzhupy/asynchttp/__init__.py
jinzhupy/rdbms/__init__.py
jinzhupy/rdbms/pg.py
jinzhupy/redis/__init__.py
jinzhupy/tools/__init__.py
jinzhupy/tools/behevior.py
jinzhupy/tools/query_builder.py
jinzhupy/tools/singleton.py
jinzhupy-1.0.21.dist-info/METADATA
jinzhupy-1.0.21.dist-info/WHEEL
jinzhupy-1.0.21.dist-info/top_level.txt
jinzhupy-1.0.21.dist-info/RECORD
