Metadata-Version: 2.1
Name: jinzhupy
Version: 1.0.21
Summary: Common python package
Home-page: https://gitee.com/brotherbabyxy/jinzhupy
Author: brotherbaby
Author-email: xyxiangyue@163.com
Classifier: Programming Language :: Python :: 3
Classifier: License :: OSI Approved :: MIT License
Classifier: Operating System :: OS Independent
Requires-Python: >=3.8
Requires-Dist: aredis>=1.1.8
Requires-Dist: aiohttp>=3.8.4
Requires-Dist: aio-pika>=9.5.2
Requires-Dist: sqlalchemy==2.0.43
Requires-Dist: asyncpg==0.27.0
